<?xml version="1.0" encoding="UTF-8"?>
<rdf:RDF	xmlns:rdf="http://www.w3.org/1999/02/22-rdf-syntax-ns#"
	xmlns:cim="http://iec.ch/TC57/2010/CIM-schema-cim15#"
	xmlns:ftn="http://www.ftnydro.com/CIM15/2010/extension#">	
	
	<cim:ConnectivityNodeContainer rdf:ID="CNC_1">
		<cim:IdentifiedObject.mRID>CNC_1</cim:IdentifiedObject.mRID>
		<cim:IdentifiedObject.name>ConnectivityNodeContainer_1</cim:IdentifiedObject.name>
	</cim:ConnectivityNodeContainer>
	
	<cim:ConnectivityNode rdf:ID="CN_1">
		<cim:ConnectivityNode.ConnectivityNodeContainer rdf:resource="#CNC_1"/>
		<cim:IdentifiedObject.mRID>CN_1</cim:IdentifiedObject.mRID>
		<cim:IdentifiedObject.name>ConnectivityNode_1</cim:IdentifiedObject.name>
	</cim:ConnectivityNode>
	
	<cim:ConnectivityNode rdf:ID="CN_4">
		<cim:ConnectivityNode.ConnectivityNodeContainer rdf:resource="#CNC_1"/>
		<cim:IdentifiedObject.mRID>CN_4</cim:IdentifiedObject.mRID>
		<cim:IdentifiedObject.name>ConnectivityNode_4</cim:IdentifiedObject.name>
	</cim:ConnectivityNode>
	
	<cim:ConnectivityNode rdf:ID="CN_7">
		<cim:ConnectivityNode.ConnectivityNodeContainer rdf:resource="#CNC_1"/>
		<cim:IdentifiedObject.mRID>CN_7</cim:IdentifiedObject.mRID>
		<cim:IdentifiedObject.name>ConnectivityNode_7</cim:IdentifiedObject.name>
	</cim:ConnectivityNode>
	
	<cim:ConnectivityNode rdf:ID="CN_8">
		<cim:ConnectivityNode.ConnectivityNodeContainer rdf:resource="#CNC_1"/>
		<cim:IdentifiedObject.mRID>CN_8</cim:IdentifiedObject.mRID>
		<cim:IdentifiedObject.name>ConnectivityNode_8</cim:IdentifiedObject.name>
	</cim:ConnectivityNode>
	
	<cim:Terminal rdf:ID="TERM_2">
		<cim:Terminal.ConductingEquipment rdf:resource="#ACLS_1"/>
		<cim:Terminal.ConnectivityNode rdf:resource="#CN_8"/>
		<cim:IdentifiedObject.mRID>TERM_2</cim:IdentifiedObject.mRID>
		<cim:IdentifiedObject.name>Terminal_2</cim:IdentifiedObject.name>
	</cim:Terminal>
	
	<cim:Terminal rdf:ID="TERM_17">
		<cim:Terminal.ConductingEquipment rdf:resource="#EC_4"/>
		<cim:Terminal.ConnectivityNode rdf:resource="#CN_7"/>
		<cim:IdentifiedObject.mRID>TERM_17</cim:IdentifiedObject.mRID>
		<cim:IdentifiedObject.name>Terminal_17</cim:IdentifiedObject.name>
	</cim:Terminal>
	
	<cim:Terminal rdf:ID="TERM_18">
		<cim:Terminal.ConductingEquipment rdf:resource="#BR_4"/>
		<cim:Terminal.ConnectivityNode rdf:resource="#CN_1"/>
		<cim:IdentifiedObject.mRID>TERM_18</cim:IdentifiedObject.mRID>
		<cim:IdentifiedObject.name>Terminal_18</cim:IdentifiedObject.name>
	</cim:Terminal>
	
	<cim:Terminal rdf:ID="TERM_19">
		<cim:Terminal.ConductingEquipment rdf:resource="#BR_4"/>
		<cim:Terminal.ConnectivityNode rdf:resource="#CN_8"/>
		<cim:IdentifiedObject.mRID>TERM_19</cim:IdentifiedObject.mRID>
		<cim:IdentifiedObject.name>Terminal_19</cim:IdentifiedObject.name>
	</cim:Terminal>
	
	<cim:Terminal rdf:ID="TERM_20">
		<cim:Terminal.ConductingEquipment rdf:resource="#EC_5"/>
		<cim:Terminal.ConnectivityNode rdf:resource="#CN_4"/>
		<cim:IdentifiedObject.mRID>TERM_20</cim:IdentifiedObject.mRID>
		<cim:IdentifiedObject.name>Terminal_20</cim:IdentifiedObject.name>
	</cim:Terminal>
	
	<cim:ACLineSegment rdf:ID="ACLS_1">
		<cim:Conductor.length></cim:Conductor.length>
		<cim:Equipment.normallyInService>true</cim:Equipment.normallyInService>
		<cim:IdentifiedObject.mRID>ACLS_1</cim:IdentifiedObject.mRID>
		<cim:IdentifiedObject.name>ACLineSegment_1</cim:IdentifiedObject.name>
	</cim:ACLineSegment>
	
	<cim:Breaker rdf:ID="BR_4">
		<cim:Switch.normalOpen>false</cim:Switch.normalOpen>
		<cim:Switch.switchOnCount></cim:Switch.switchOnCount>
		<cim:Switch.switchOnDate></cim:Switch.switchOnDate>
		<cim:Equipment.normallyInService>true</cim:Equipment.normallyInService>
		<cim:IdentifiedObject.mRID>BR_4</cim:IdentifiedObject.mRID>
		<cim:IdentifiedObject.name>Breaker_4</cim:IdentifiedObject.name>
	</cim:Breaker>
		
	<cim:EnergyConsumer rdf:ID="EC_5">
		<cim:EnergyConsumer.pfixed></cim:EnergyConsumer.pfixed>
		<cim:EnergyConsumer.qfixed></cim:EnergyConsumer.qfixed>
		<cim:Equipment.normallyInService>true</cim:Equipment.normallyInService>
		<cim:IdentifiedObject.mRID>EC_5</cim:IdentifiedObject.mRID>
		<cim:IdentifiedObject.name>EnergyConsumer_5</cim:IdentifiedObject.name>
	</cim:EnergyConsumer>

</rdf:RDF>